[
    {
     "Breed": "Abyssinian",
     "Location of origin": "Ethiopia"
    },
    {
     "Breed": "Aegean",
     "Location of origin": "Greece"
    },
    {
     "Breed": "American Bobtail",
     "Location of origin": "United States"
    },
    {
     "Breed": "American Curl",
     "Location of origin": "United States"
    },
    {
     "Breed": "American Ringtail",
     "Location of origin": "United States"
    },
    {
     "Breed": "American Shorthair",
     "Location of origin": "United States"
    },
    {
     "Breed": "American Wirehair",
     "Location of origin": "United States"
    },
    {
     "Breed": "Aphrodite Giant",
     "Location of origin": "Cyprus"
    },
    {
     "Breed": "Arabian Mau",
     "Location of origin": "the Arabian Peninsula"
    },
    {
     "Breed": "Asian",
     "Location of origin": "Asia"
    },
    {
     "Breed": "Asian Semi-longhair",
     "Location of origin": "United Kingdom"
    },
    {
     "Breed": "Australian Mist",
     "Location of origin": "Australia"
    },
    {
     "Breed": "Balinese",
     "Location of origin": "Thailand"
    },
    {
     "Breed": "Bambino",
     "Location of origin": "United States"
    },
    {
     "Breed": "Bengal",
     "Location of origin": "Asia"
    },
    {
     "Breed": "Birman",
     "Location of origin": "Burma (Myanmar)"
    },
    {
     "Breed": "Bombay",
     "Location of origin": "United States and Burma (Myanmar)"
    },
    {
     "Breed": "Brazilian Shorthair",
     "Location of origin": "Brazil"
    },
    {
     "Breed": "British Longhair",
     "Location of origin": "England"
    },
    {
     "Breed": "British Shorthair",
     "Location of origin": "England"
    },
    {
     "Breed": "Burmese",
     "Location of origin": "Burma (Myanmar)"
    },
    {
     "Breed": "Burmilla",
     "Location of origin": "England"
    },
    {
     "Breed": "California Spangled",
     "Location of origin": "United States"
    },
    {
     "Breed": "Chantilly-Tiffany",
     "Location of origin": "United States"
    },
    {
     "Breed": "Chartreux",
     "Location of origin": "France"
    },
    {
     "Breed": "Chausie",
     "Location of origin": "United States"
    },
    {
     "Breed": "Colorpoint Shorthair",
     "Location of origin": "England, United Kingdom"
    },
    {
     "Breed": "Cornish Rex",
     "Location of origin": "Cornwall, England,"
    },
    {
     "Breed": "Cymric, Manx Longhair or Long-haired Manx[a]",
     "Location of origin": "the Isle of Man, United States, and Canada&nbsp;[b][8]"
    },
    {
     "Breed": "Cyprus",
     "Location of origin": "Cyprus"
    },
    {
     "Breed": "Devon Rex",
     "Location of origin": "Buckfastleigh, Devon, England, United Kingdom"
    },
    {
     "Breed": "Don Sphynx",
     "Location of origin": "Russia"
    },
    {
     "Breed": "Chinese Li Hua",
     "Location of origin": "China"
    },
    {
     "Breed": "Dwelf",
     "Location of origin": "United States"
    },
    {
     "Breed": "Egyptian Mau",
     "Location of origin": "Egypt"
    },
    {
     "Breed": "European Shorthair",
     "Location of origin": "Continental Europe"
    },
    {
     "Breed": "Exotic Shorthair",
     "Location of origin": "United States"
    },
    {
     "Breed": "Foldex",
     "Location of origin": "Canada"
    },
    {
     "Breed": "German Rex",
     "Location of origin": "Germany"
    },
    {
     "Breed": "Havana Brown",
     "Location of origin": "Thailand"
    },
    {
     "Breed": "Highlander",
     "Location of origin": "United States"
    },
    {
     "Breed": "Himalayan",
     "Location of origin": "United States and United Kingdom"
    },
    {
     "Breed": "Japanese Bobtail",
     "Location of origin": "Japan"
    },
    {
     "Breed": "Javanese",
     "Location of origin": "Southeast Asia"
    },
    {
     "Breed": "Kanaani",
     "Location of origin": "Germany"
    },
    {
     "Breed": "Khao Manee",
     "Location of origin": "Thailand"
    },
    {
     "Breed": "Kinkalow",
     "Location of origin": "United States"
    },
    {
     "Breed": "Korat",
     "Location of origin": "Thailand"
    },
    {
     "Breed": "Korean Bobtail",
     "Location of origin": "Korea"
    },
    {
     "Breed": "Korn Ja",
     "Location of origin": "Thailand"
    },
    {
     "Breed": "Kurilian Bobtail",
     "Location of origin": "eastern Russia and Japan"
    },
    {
     "Breed": "Lambkin",
     "Location of origin": "United States"
    },
    {
     "Breed": "LaPerm",
     "Location of origin": "United States"
    },
    {
     "Breed": "Lykoi",
     "Location of origin": "United States"
    },
    {
     "Breed": "Maine Coon",
     "Location of origin": "United States"
    },
    {
     "Breed": "Manx",
     "Location of origin": "the Isle of Man"
    },
    {
     "Breed": "Mekong Bobtail",
     "Location of origin": "Russia"
    },
    {
     "Breed": "Minskin",
     "Location of origin": "United States"
    },
    {
     "Breed": "Minuet",
     "Location of origin": "United States"
    },
    {
     "Breed": "Munchkin",
     "Location of origin": "United States"
    },
    {
     "Breed": "Nebelung",
     "Location of origin": "United States"
    },
    {
     "Breed": "Norwegian Forest Cat",
     "Location of origin": "Norway"
    },
    {
     "Breed": "Ocicat",
     "Location of origin": "United States"
    },
    {
     "Breed": "Ojos Azules",
     "Location of origin": "United States"
    },
    {
     "Breed": "Oregon Rex",
     "Location of origin": "United States"
    },
    {
     "Breed": "Oriental Bicolor",
     "Location of origin": "Thailand"
    },
    {
     "Breed": "Oriental Longhair",
     "Location of origin": "Thailand"
    },
    {
     "Breed": "Oriental Shorthair",
     "Location of origin": "Thailand"
    },
    {
     "Breed": "Persian (modern)",
     "Location of origin": "Greater Iran"
    },
    {
     "Breed": "Persian (traditional)",
     "Location of origin": "Greater Iran"
    },
    {
     "Breed": "Peterbald",
     "Location of origin": "Russia"
    },
    {
     "Breed": "Pixie-bob",
     "Location of origin": "United States"
    },
    {
     "Breed": "Raas",
     "Location of origin": "Raas Island"
    },
    {
     "Breed": "Ragamuffin",
     "Location of origin": "United States"
    },
    {
     "Breed": "Ragdoll",
     "Location of origin": "United States"
    },
    {
     "Breed": "Russian Blue",
     "Location of origin": "Russia"
    },
    {
     "Breed": "Russian White, Russian Black and Russian Tabby",
     "Location of origin": "Russia"
    },
    {
     "Breed": "Sam Sawet",
     "Location of origin": "Thailand"
    },
    {
     "Breed": "Savannah",
     "Location of origin": "United States"
    },
    {
     "Breed": "Scottish Fold",
     "Location of origin": "Scotland"
    },
    {
     "Breed": "Selkirk Rex",
     "Location of origin": "United States"
    },
    {
     "Breed": "Serengeti",
     "Location of origin": "United States"
    },
    {
     "Breed": "Serrade Petit",
     "Location of origin": "France"
    },
    {
     "Breed": "Siamese",
     "Location of origin": "Thailand"
    },
    {
     "Breed": "Siberian",
     "Location of origin": "Russia, Ukraine"
    },
    {
     "Breed": "Singapura",
     "Location of origin": "Singapore"
    },
    {
     "Breed": "Snowshoe",
     "Location of origin": "United States"
    },
    {
     "Breed": "Sokoke",
     "Location of origin": "Kenya"
    },
    {
     "Breed": "Somali",
     "Location of origin": "United States, Canada"
    },
    {
     "Breed": "Sphynx",
     "Location of origin": "Canada, Europe"
    },
    {
     "Breed": "Suphalak",
     "Location of origin": "Thailand"
    },
    {
     "Breed": "Thai Lilac, Thai Blue Point and Thai Lilac Point",
     "Location of origin": "Thailand"
    },
    {
     "Breed": "Thai",
     "Location of origin": "Thailand"
    },
    {
     "Breed": "Tonkinese",
     "Location of origin": "Canada, United States"
    },
    {
     "Breed": "Toybob",
     "Location of origin": "Russia"
    },
    {
     "Breed": "Toyger",
     "Location of origin": "United States"
    },
    {
     "Breed": "Turkish Angora",
     "Location of origin": "Turkey"
    },
    {
     "Breed": "Turkish Van",
     "Location of origin": "Turkey"
    },
    {
     "Breed": "Turkish Vankedisi",
     "Location of origin": "Turkey"
    },
    {
     "Breed": "Ukrainian Levkoy",
     "Location of origin": "Ukraine"
    },
    {
     "Breed": "York Chocolate",
     "Location of origin": "New York, United States"
    }
   ]